serix/__init__.py
serix/__main__.py
serix/py.typed
serix/adapters/__init__.py
serix/adapters/openai.py
serix/cli/__init__.py
serix/cli/legacy.py
serix/cli/commands/__init__.py
serix/cli/commands/demo_cmd.py
serix/cli/commands/dev_cmd.py
serix/cli/commands/init_cmd.py
serix/cli/commands/status_cmd.py
serix/cli/commands/test_cmd.py
serix/cli/output/__init__.py
serix/cli/output/github.py
serix/cli/output/static.py
serix/core/__init__.py
serix/core/client.py
serix/core/config_loader.py
serix/core/constants.py
serix/core/errors.py
serix/core/events.py
serix/core/protocols.py
serix/core/recorder.py
serix/core/target.py
serix/core/types.py
serix/eval/__init__.py
serix/eval/classifier.py
serix/eval/evaluator.py
serix/eval/remediation.py
serix/eval/rubric.py
serix/examples/__init__.py
serix/examples/golden_victim.py
serix/fuzz/__init__.py
serix/fuzz/adversary.py
serix/fuzz/engine.py
serix/fuzz/mutations.py
serix/fuzz/redteam.py
serix/fuzz/scenarios.py
serix/fuzz/personas/__init__.py
serix/fuzz/personas/base.py
serix/fuzz/personas/confuser.py
serix/fuzz/personas/extractor.py
serix/fuzz/personas/jailbreaker.py
serix/fuzz/personas/manipulator.py
serix/heal/__init__.py
serix/heal/analyzer.py
serix/heal/engine.py
serix/heal/patcher.py
serix/heal/types.py
serix/integrations/__init__.py
serix/integrations/crewai.py
serix/integrations/langchain.py
serix/regression/__init__.py
serix/regression/runner.py
serix/regression/store.py
serix/report/__init__.py
serix/report/console.py
serix/report/github.py
serix/report/html.py
serix/report/json_export.py
serix/report/live_ui.py
serix/report/templates/report.html
serix/sdk/__init__.py
serix/sdk/decorator.py
serix/services/__init__.py
serix/services/attack.py
serix/services/config.py
serix/services/healing.py
serix/services/interceptor.py
serix/services/judge.py
serix/services/regression.py
serix/services/report.py
serix/services/storage.py
serix/services/target.py
serix/ui/__init__.py
serix/ui/render.py
serix/ui/theme.py
serix-0.2.9.dist-info/METADATA
serix-0.2.9.dist-info/WHEEL
serix-0.2.9.dist-info/entry_points.txt
serix-0.2.9.dist-info/licenses/LICENSE
serix-0.2.9.dist-info/RECORD
