Metadata-Version: 2.4
Name: serix
Version: 0.2.9
Summary: Automated adversarial testing for AI agents
Project-URL: Homepage, https://github.com/yuktathapliyal/serix
Project-URL: Repository, https://github.com/yuktathapliyal/serix
Project-URL: Documentation, https://github.com/yuktathapliyal/serix#readme
Author-email: Yukta Thapliyal <yukta@serixlabs.com>
License: MIT
License-File: LICENSE
Keywords: agents,fuzzing,red-teaming,security,testing
Classifier: Development Status :: 4 - Beta
Classifier: Environment :: Console
Classifier: Intended Audience :: Developers
Classifier: Intended Audience :: Science/Research
Classifier: License :: OSI Approved :: MIT License
Classifier: Programming Language :: Python :: 3.11
Classifier: Programming Language :: Python :: 3.12
Classifier: Topic :: Scientific/Engineering :: Artificial Intelligence
Classifier: Topic :: Security
Classifier: Topic :: Software Development :: Testing
Classifier: Typing :: Typed
Requires-Python: >=3.11
Requires-Dist: httpx>=0.25.0
Requires-Dist: jinja2>=3.1.0
Requires-Dist: openai>=1.0.0
Requires-Dist: pydantic>=2.0.0
Requires-Dist: python-dotenv>=1.0.0
Requires-Dist: rich>=13.0.0
Requires-Dist: tomli>=2.0.0; python_version < '3.11'
Requires-Dist: typer>=0.9.0
